[{"name":"\u0413\u041e\u0421\u0422 11530-76","diameters":[{"name":"22.00","longs":[{"long":"135.00","weight":"448.00000000"},{"long":"140.00","weight":"449.00000000"}]},{"name":"24.00","longs":[{"long":"140.00","weight":"522.00000000"},{"long":"150.00","weight":"585.00000000"},{"long":"160.00","weight":"592.00000000"}]},{"name":"27.00","longs":[{"long":"160.00","weight":"818.00000000"},{"long":"170.00","weight":"827.00000000"},{"long":"180.00","weight":"872.00000000"}]}]},{"name":"\u0413\u041e\u0421\u0422 11532-76","diameters":[{"name":"22.00","longs":[{"long":"0.00","weight":"152.00000000"}]},{"name":"24.00","longs":[{"long":"0.00","weight":"153.00000000"}]},{"name":"27.00","longs":[{"long":"0.00","weight":"220.00000000"}]}]},{"name":"\u0413\u041e\u0421\u0422 799-73","diameters":[{"name":"22.00","longs":[{"long":"115.00","weight":"400.00000000"}]}]},{"name":"\u0413\u041e\u0421\u0422 809-71","diameters":[{"name":"24.00","longs":[{"long":"170.00","weight":"0.56000000"}]}]},{"name":"\u0413\u041e\u0421\u0422 8144-73","diameters":[{"name":"12.00","longs":[{"long":"58.00","weight":"59.15999985"}]},{"name":"16.00","longs":[{"long":"72.00","weight":"135.83000183"}]},{"name":"18.00","longs":[{"long":"88.00","weight":"207.41999817"}]}]}]